hybridmethods/__init__.py
hybridmethods/cl.py
hybridmethods-0.1.3.dist-info/LICENSE
hybridmethods-0.1.3.dist-info/WHEEL
hybridmethods-0.1.3.dist-info/METADATA
hybridmethods-0.1.3.dist-info/RECORD
