Metadata-Version: 2.1
Name: hybridmethods
Version: 0.1.3
Summary: Library to create hybrids of class methods and instance methods
License: 0BSD
Keywords: hybridmethod,method,methods,utility
Author: Dense Reptile
Author-email: 80247368+DenseReptile@users.noreply.github.com
Requires-Python: >=3.7
Classifier: Intended Audience :: Developers
Classifier: License :: OSI Approved :: BSD License
Classifier: License :: Other/Proprietary License
Classifier: Programming Language :: Python :: 3
Classifier: Programming Language :: Python :: 3 :: Only
Classifier: Programming Language :: Python :: 3.10
Classifier: Programming Language :: Python :: 3.7
Classifier: Programming Language :: Python :: 3.8
Classifier: Programming Language :: Python :: 3.9
